imaparchiver/__init__.py
imaparchiver/main.py
IMAPArchiver-1.0.0.dist-info/LICENSE
IMAPArchiver-1.0.0.dist-info/METADATA
IMAPArchiver-1.0.0.dist-info/WHEEL
IMAPArchiver-1.0.0.dist-info/entry_points.txt
IMAPArchiver-1.0.0.dist-info/top_level.txt
IMAPArchiver-1.0.0.dist-info/RECORD
