Metadata-Version: 2.1
Name: IMAPArchiver
Version: 1.0.0
Summary: The IMAPArchiver is a command-line tool that exports emails from your IMAP mailbox to a local folder, helping you keep your mailbox organized and your data backed up.
Home-page: https://github.com/flojud/IMAPArchiver
Author: flojud
Author-email: dev.flojud@gmail.com
License: MIT
Project-URL: Bug Tracker, https://github.com/flojud/IMAPArchiver/issues
Keywords: imap email export backup archive
Requires-Python: >=3.11
License-File: LICENSE
